pystator/__init__.py
pystator/builder.py
pystator/cli.py
pystator/idempotency.py
pystator/observability.py
pystator/py.typed
pystator/visualization.py
pystator/actions/__init__.py
pystator/actions/executor.py
pystator/actions/registry.py
pystator/actions/retry.py
pystator/api/__init__.py
pystator/api/main.py
pystator/api/dependencies/__init__.py
pystator/api/dependencies/core.py
pystator/api/dependencies/database.py
pystator/api/models/__init__.py
pystator/api/models/requests.py
pystator/api/models/responses.py
pystator/api/routes/__init__.py
pystator/api/routes/v1/__init__.py
pystator/api/routes/v1/machines.py
pystator/api/routes/v1/process.py
pystator/api/routes/v1/settings.py
pystator/api/routes/v1/templates.py
pystator/api/services/__init__.py
pystator/api/services/fsm_service.py
pystator/config/__init__.py
pystator/config/converter.py
pystator/config/database.py
pystator/config/loader.py
pystator/config/models.py
pystator/config/validator.py
pystator/contrib/__init__.py
pystator/contrib/order/__init__.py
pystator/contrib/order/fsm/order_fsm.yaml
pystator/contrib/rebalance/__init__.py
pystator/contrib/rebalance/fsm/rebalance_fsm.yaml
pystator/core/__init__.py
pystator/core/errors.py
pystator/core/event.py
pystator/core/invoke.py
pystator/core/machine.py
pystator/core/parallel.py
pystator/core/state.py
pystator/core/state_hierarchy.py
pystator/core/state_store.py
pystator/core/transition.py
pystator/db/__init__.py
pystator/db/base.py
pystator/db/migrations/env.py
pystator/db/migrations/versions/20260130000000_initial_machines.py
pystator/db/migrations/versions/__init__.py
pystator/db/models/__init__.py
pystator/db/models/machine.py
pystator/guards/__init__.py
pystator/guards/builtins.py
pystator/guards/evaluator.py
pystator/guards/registry.py
pystator/orchestration/__init__.py
pystator/orchestration/invoke.py
pystator/orchestration/orchestrator.py
pystator/recipes/__init__.py
pystator/recipes/actions.py
pystator/recipes/context.py
pystator/recipes/guards.py
pystator-0.0.1.dist-info/licenses/LICENSE
pystator-0.0.1.dist-info/METADATA
pystator-0.0.1.dist-info/WHEEL
pystator-0.0.1.dist-info/entry_points.txt
pystator-0.0.1.dist-info/top_level.txt
pystator-0.0.1.dist-info/RECORD
