Metadata-Version: 2.4
Name: pystator
Version: 0.0.1
Summary: A configuration-driven, stateless finite state machine library for Python
Author-email: StatFYI <contact@statfyi.com>
License: MIT
Project-URL: Homepage, https://github.com/statfyi/pystator
Project-URL: Documentation, https://github.com/statfyi/pystator#readme
Project-URL: Repository, https://github.com/statfyi/pystator
Project-URL: Issues, https://github.com/statfyi/pystator/issues
Project-URL: Changelog, https://github.com/statfyi/pystator/blob/main/CHANGELOG.md
Keywords: state-machine,fsm,finite-state-machine,workflow,configuration-driven,declarative,guards,transitions,order-management,event-driven
Classifier: Development Status :: 4 - Beta
Classifier: Intended Audience :: Developers
Classifier: License :: OSI Approved :: MIT License
Classifier: Operating System :: OS Independent
Classifier: Programming Language :: Python :: 3
Classifier: Programming Language :: Python :: 3.10
Classifier: Programming Language :: Python :: 3.11
Classifier: Programming Language :: Python :: 3.12
Classifier: Programming Language :: Python :: 3.13
Classifier: Typing :: Typed
Classifier: Topic :: Software Development :: Libraries :: Python Modules
Classifier: Topic :: Software Development :: Libraries :: Application Frameworks
Requires-Python: >=3.10
License-File: LICENSE
Requires-Dist: pyyaml>=6.0
Requires-Dist: pydantic>=2.0.0
Provides-Extra: dev
Requires-Dist: pytest>=7.4.0; extra == "dev"
Requires-Dist: pytest-cov>=4.1.0; extra == "dev"
Requires-Dist: ruff>=0.4.0; extra == "dev"
Requires-Dist: mypy>=1.8.0; extra == "dev"
Requires-Dist: build>=1.0.0; extra == "dev"
Requires-Dist: twine>=5.0.0; extra == "dev"
Requires-Dist: types-PyYAML>=6.0.0; extra == "dev"
Provides-Extra: api
Requires-Dist: fastapi>=0.104.0; extra == "api"
Requires-Dist: uvicorn[standard]>=0.24.0; extra == "api"
Requires-Dist: pydantic>=2.0.0; extra == "api"
Requires-Dist: pydantic-settings>=2.0.0; extra == "api"
Requires-Dist: python-multipart>=0.0.6; extra == "api"
Requires-Dist: sqlalchemy>=2.0.0; extra == "api"
Provides-Extra: ui
Requires-Dist: fastapi>=0.104.0; extra == "ui"
Requires-Dist: uvicorn[standard]>=0.24.0; extra == "ui"
Requires-Dist: httpx>=0.24.0; extra == "ui"
Requires-Dist: aiofiles>=23.0.0; extra == "ui"
Provides-Extra: recipes
Requires-Dist: simpleeval>=0.9.0; extra == "recipes"
Requires-Dist: httpx>=0.24.0; extra == "recipes"
Dynamic: license-file
